[
  {
    "author": "LMB Studio",
    "link_thumb": "https://live.staticflickr.com/65535/51781179955_6c73f7ced9_o.gif",
    "link_bin": "https://github.com/lmbstudiocontact/mb5_10/raw/main/OnePunchManAnime_L1_-1470275093.bin",
    "id_bin": "OnePunchManAnime_L1_-1470275093",
    "list_language": [],
    "array_tags": [
      "lmbstudio"
    ],
    "list_album": [
      {
        "id_album": "-1626855614",
        "link_thumb": "https://live.staticflickr.com/65535/51781179955_6c73f7ced9_o.gif",
        "title": "One Punch Man Anime_L1"
      }
    ]
  },
  {
    "author": "LMB Studio",
    "link_thumb": "https://live.staticflickr.com/65535/51781179885_f43fcecb81_o.gif",
    "link_bin": "https://github.com/lmbstudiocontact/mb5_10/raw/main/OnePunchManAnime_L1_-2067664421.bin",
    "id_bin": "OnePunchManAnime_L1_-2067664421",
    "list_language": [],
    "array_tags": [
      "lmbstudio"
    ],
    "list_album": [
      {
        "id_album": "-1626855614",
        "link_thumb": "https://live.staticflickr.com/65535/51781179885_f43fcecb81_o.gif",
        "title": "One Punch Man Anime_L1"
      }
    ]
  }
]