[
  {
    "author": "LMB Studio",
    "link_thumb": "https://live.staticflickr.com/65535/51788127940_9f3a370286_o.gif",
    "link_bin": "https://github.com/lmbstudiocontact/mb5_25/raw/main/Shiv_L3_-1089269698.bin",
    "id_bin": "Shiv_L3_-1089269698",
    "list_language": [
      {
        "author": "LMB Studio",
        "link_thumb": "https://live.staticflickr.com/65535/51787256246_53f9158357_o.gif",
        "link_bin": "https://github.com/lmbstudiocontact/mb5_25/raw/main/Shiv_L3_-1089269698_English.bin",
        "name_language": "English",
        "id_bin_language": "Shiv_L3_-1089269698_English"
      },
      {
        "author": "LMB Studio",
        "link_thumb": "https://live.staticflickr.com/65535/51788127825_8b23c2aca4_o.gif",
        "link_bin": "https://github.com/lmbstudiocontact/mb5_25/raw/main/Shiv_L3_-1089269698_Portuguese.bin",
        "name_language": "Portuguese",
        "id_bin_language": "Shiv_L3_-1089269698_Portuguese"
      },
      {
        "author": "LMB Studio",
        "link_thumb": "https://live.staticflickr.com/65535/51787879219_84893312df_o.gif",
        "link_bin": "https://github.com/lmbstudiocontact/mb5_25/raw/main/Shiv_L3_-1089269698_Russian.bin",
        "name_language": "Russian",
        "id_bin_language": "Shiv_L3_-1089269698_Russian"
      },
      {
        "author": "LMB Studio",
        "link_thumb": "https://live.staticflickr.com/65535/51787506193_f1ecbf0ddc_o.gif",
        "link_bin": "https://github.com/lmbstudiocontact/mb5_25/raw/main/Shiv_L3_-1089269698_Spanish.bin",
        "name_language": "Spanish",
        "id_bin_language": "Shiv_L3_-1089269698_Spanish"
      }
    ],
    "array_tags": [
      "lmbstudio"
    ],
    "list_album": [
      {
        "id_album": "-568595356",
        "link_thumb": "https://live.staticflickr.com/65535/51788127940_9f3a370286_o.gif",
        "title": "Shiv_L3"
      }
    ]
  },
  {
    "author": "LMB Studio",
    "link_thumb": "https://live.staticflickr.com/65535/51788127370_b744a694a2_o.gif",
    "link_bin": "https://github.com/lmbstudiocontact/mb5_25/raw/main/Shiv_L3_-1290688604.bin",
    "id_bin": "Shiv_L3_-1290688604",
    "list_language": [
      {
        "author": "LMB Studio",
        "link_thumb": "https://live.staticflickr.com/65535/51786438157_b74b97369e_o.gif",
        "link_bin": "https://github.com/lmbstudiocontact/mb5_25/raw/main/Shiv_L3_-1290688604_English.bin",
        "name_language": "English",
        "id_bin_language": "Shiv_L3_-1290688604_English"
      },
      {
        "author": "LMB Studio",
        "link_thumb": "https://live.staticflickr.com/65535/51787505728_2a2bc4513e_o.gif",
        "link_bin": "https://github.com/lmbstudiocontact/mb5_25/raw/main/Shiv_L3_-1290688604_Portuguese.bin",
        "name_language": "Portuguese",
        "id_bin_language": "Shiv_L3_-1290688604_Portuguese"
      },
      {
        "author": "LMB Studio",
        "link_thumb": "https://live.staticflickr.com/65535/51787505673_9bb1dbfb97_o.gif",
        "link_bin": "https://github.com/lmbstudiocontact/mb5_25/raw/main/Shiv_L3_-1290688604_Russian.bin",
        "name_language": "Russian",
        "id_bin_language": "Shiv_L3_-1290688604_Russian"
      },
      {
        "author": "LMB Studio",
        "link_thumb": "https://live.staticflickr.com/65535/51786437977_ec14d04b8c_o.gif",
        "link_bin": "https://github.com/lmbstudiocontact/mb5_25/raw/main/Shiv_L3_-1290688604_Spanish.bin",
        "name_language": "Spanish",
        "id_bin_language": "Shiv_L3_-1290688604_Spanish"
      }
    ],
    "array_tags": [
      "lmbstudio"
    ],
    "list_album": [
      {
        "id_album": "-568595356",
        "link_thumb": "https://live.staticflickr.com/65535/51788127370_b744a694a2_o.gif",
        "title": "Shiv_L3"
      }
    ]
  },
  {
    "author": "LMB Studio",
    "link_thumb": "https://live.staticflickr.com/65535/51786437897_e608c68df8_o.gif",
    "link_bin": "https://github.com/lmbstudiocontact/mb5_25/raw/main/Shiv_L3_-1376040381.bin",
    "id_bin": "Shiv_L3_-1376040381",
    "list_language": [
      {
        "author": "LMB Studio",
        "link_thumb": "https://live.staticflickr.com/65535/51786437827_3c8efee4ec_o.gif",
        "link_bin": "https://github.com/lmbstudiocontact/mb5_25/raw/main/Shiv_L3_-1376040381_English.bin",
        "name_language": "English",
        "id_bin_language": "Shiv_L3_-1376040381_English"
      },
      {
        "author": "LMB Studio",
        "link_thumb": "https://live.staticflickr.com/65535/51786437742_f9a215a7a2_o.gif",
        "link_bin": "https://github.com/lmbstudiocontact/mb5_25/raw/main/Shiv_L3_-1376040381_Portuguese.bin",
        "name_language": "Portuguese",
        "id_bin_language": "Shiv_L3_-1376040381_Portuguese"
      },
      {
        "author": "LMB Studio",
        "link_thumb": "https://live.staticflickr.com/65535/51787255276_7914046347_o.gif",
        "link_bin": "https://github.com/lmbstudiocontact/mb5_25/raw/main/Shiv_L3_-1376040381_Russian.bin",
        "name_language": "Russian",
        "id_bin_language": "Shiv_L3_-1376040381_Russian"
      },
      {
        "author": "LMB Studio",
        "link_thumb": "https://live.staticflickr.com/65535/51787255176_53e024bd25_o.gif",
        "link_bin": "https://github.com/lmbstudiocontact/mb5_25/raw/main/Shiv_L3_-1376040381_Spanish.bin",
        "name_language": "Spanish",
        "id_bin_language": "Shiv_L3_-1376040381_Spanish"
      }
    ],
    "array_tags": [
      "lmbstudio"
    ],
    "list_album": [
      {
        "id_album": "-568595356",
        "link_thumb": "https://live.staticflickr.com/65535/51786437897_e608c68df8_o.gif",
        "title": "Shiv_L3"
      }
    ]
  },
  {
    "author": "LMB Studio",
    "link_thumb": "https://live.staticflickr.com/65535/51786442732_1462e64332_o.gif",
    "link_bin": "https://github.com/lmbstudiocontact/mb5_25/raw/main/Shiv_L3_-140695313.bin",
    "id_bin": "Shiv_L3_-140695313",
    "list_language": [
      {
        "author": "LMB Studio",
        "link_thumb": "https://live.staticflickr.com/65535/51787510218_eec73f91c5_o.gif",
        "link_bin": "https://github.com/lmbstudiocontact/mb5_25/raw/main/Shiv_L3_-140695313_English.bin",
        "name_language": "English",
        "id_bin_language": "Shiv_L3_-140695313_English"
      },
      {
        "author": "LMB Studio",
        "link_thumb": "https://live.staticflickr.com/65535/51787510173_dab92d28ab_o.gif",
        "link_bin": "https://github.com/lmbstudiocontact/mb5_25/raw/main/Shiv_L3_-140695313_Portuguese.bin",
        "name_language": "Portuguese",
        "id_bin_language": "Shiv_L3_-140695313_Portuguese"
      },
      {
        "author": "LMB Studio",
        "link_thumb": "https://live.staticflickr.com/65535/51787882929_e5b5444c95_o.gif",
        "link_bin": "https://github.com/lmbstudiocontact/mb5_25/raw/main/Shiv_L3_-140695313_Russian.bin",
        "name_language": "Russian",
        "id_bin_language": "Shiv_L3_-140695313_Russian"
      },
      {
        "author": "LMB Studio",
        "link_thumb": "https://live.staticflickr.com/65535/51788131185_8134467b50_o.gif",
        "link_bin": "https://github.com/lmbstudiocontact/mb5_25/raw/main/Shiv_L3_-140695313_Spanish.bin",
        "name_language": "Spanish",
        "id_bin_language": "Shiv_L3_-140695313_Spanish"
      }
    ],
    "array_tags": [
      "lmbstudio"
    ],
    "list_album": [
      {
        "id_album": "-568595356",
        "link_thumb": "https://live.staticflickr.com/65535/51786442732_1462e64332_o.gif",
        "title": "Shiv_L3"
      }
    ]
  },
  {
    "author": "LMB Studio",
    "link_thumb": "https://live.staticflickr.com/65535/51786436822_eb98ab2a58_o.gif",
    "link_bin": "https://github.com/lmbstudiocontact/mb5_25/raw/main/Shiv_L3_-1698514123.bin",
    "id_bin": "Shiv_L3_-1698514123",
    "list_language": [
      {
        "author": "LMB Studio",
        "link_thumb": "https://live.staticflickr.com/65535/51787254361_531ca7534f_o.gif",
        "link_bin": "https://github.com/lmbstudiocontact/mb5_25/raw/main/Shiv_L3_-1698514123_English.bin",
        "name_language": "English",
        "id_bin_language": "Shiv_L3_-1698514123_English"
      },
      {
        "author": "LMB Studio",
        "link_thumb": "https://live.staticflickr.com/65535/51787877549_a5cea92b7d_o.gif",
        "link_bin": "https://github.com/lmbstudiocontact/mb5_25/raw/main/Shiv_L3_-1698514123_Portuguese.bin",
        "name_language": "Portuguese",
        "id_bin_language": "Shiv_L3_-1698514123_Portuguese"
      },
      {
        "author": "LMB Studio",
        "link_thumb": "https://live.staticflickr.com/65535/51787254266_b7b895bcc8_o.gif",
        "link_bin": "https://github.com/lmbstudiocontact/mb5_25/raw/main/Shiv_L3_-1698514123_Russian.bin",
        "name_language": "Russian",
        "id_bin_language": "Shiv_L3_-1698514123_Russian"
      },
      {
        "author": "LMB Studio",
        "link_thumb": "https://live.staticflickr.com/65535/51787877404_9dafbc0c53_o.gif",
        "link_bin": "https://github.com/lmbstudiocontact/mb5_25/raw/main/Shiv_L3_-1698514123_Spanish.bin",
        "name_language": "Spanish",
        "id_bin_language": "Shiv_L3_-1698514123_Spanish"
      }
    ],
    "array_tags": [
      "lmbstudio"
    ],
    "list_album": [
      {
        "id_album": "-568595356",
        "link_thumb": "https://live.staticflickr.com/65535/51786436822_eb98ab2a58_o.gif",
        "title": "Shiv_L3"
      }
    ]
  },
  {
    "author": "LMB Studio",
    "link_thumb": "https://live.staticflickr.com/65535/51787503813_a9acde82f1_o.gif",
    "link_bin": "https://github.com/lmbstudiocontact/mb5_25/raw/main/Shiv_L3_-1729156601.bin",
    "id_bin": "Shiv_L3_-1729156601",
    "list_language": [
      {
        "author": "LMB Studio",
        "link_thumb": "https://live.staticflickr.com/65535/51787253496_71b613c7b3_o.gif",
        "link_bin": "https://github.com/lmbstudiocontact/mb5_25/raw/main/Shiv_L3_-1729156601_English.bin",
        "name_language": "English",
        "id_bin_language": "Shiv_L3_-1729156601_English"
      },
      {
        "author": "LMB Studio",
        "link_thumb": "https://live.staticflickr.com/65535/51786435797_9610b03874_o.gif",
        "link_bin": "https://github.com/lmbstudiocontact/mb5_25/raw/main/Shiv_L3_-1729156601_Portuguese.bin",
        "name_language": "Portuguese",
        "id_bin_language": "Shiv_L3_-1729156601_Portuguese"
      },
      {
        "author": "LMB Studio",
        "link_thumb": "https://live.staticflickr.com/65535/51787503588_e3639d9b51_o.gif",
        "link_bin": "https://github.com/lmbstudiocontact/mb5_25/raw/main/Shiv_L3_-1729156601_Russian.bin",
        "name_language": "Russian",
        "id_bin_language": "Shiv_L3_-1729156601_Russian"
      },
      {
        "author": "LMB Studio",
        "link_thumb": "https://live.staticflickr.com/65535/51787503538_7ae0c09769_o.gif",
        "link_bin": "https://github.com/lmbstudiocontact/mb5_25/raw/main/Shiv_L3_-1729156601_Spanish.bin",
        "name_language": "Spanish",
        "id_bin_language": "Shiv_L3_-1729156601_Spanish"
      }
    ],
    "array_tags": [
      "lmbstudio"
    ],
    "list_album": [
      {
        "id_album": "-568595356",
        "link_thumb": "https://live.staticflickr.com/65535/51787503813_a9acde82f1_o.gif",
        "title": "Shiv_L3"
      }
    ]
  },
  {
    "author": "LMB Studio",
    "link_thumb": "https://live.staticflickr.com/65535/51786435612_b3923148ff_o.gif",
    "link_bin": "https://github.com/lmbstudiocontact/mb5_25/raw/main/Shiv_L3_-1731372392.bin",
    "id_bin": "Shiv_L3_-1731372392",
    "list_language": [
      {
        "author": "LMB Studio",
        "link_thumb": "https://live.staticflickr.com/65535/51787503408_8d28f7e44a_o.gif",
        "link_bin": "https://github.com/lmbstudiocontact/mb5_25/raw/main/Shiv_L3_-1731372392_English.bin",
        "name_language": "English",
        "id_bin_language": "Shiv_L3_-1731372392_English"
      },
      {
        "author": "LMB Studio",
        "link_thumb": "https://live.staticflickr.com/65535/51787876214_85f042d514_o.gif",
        "link_bin": "https://github.com/lmbstudiocontact/mb5_25/raw/main/Shiv_L3_-1731372392_Portuguese.bin",
        "name_language": "Portuguese",
        "id_bin_language": "Shiv_L3_-1731372392_Portuguese"
      },
      {
        "author": "LMB Studio",
        "link_thumb": "https://live.staticflickr.com/65535/51787876144_c217306a8d_o.gif",
        "link_bin": "https://github.com/lmbstudiocontact/mb5_25/raw/main/Shiv_L3_-1731372392_Russian.bin",
        "name_language": "Russian",
        "id_bin_language": "Shiv_L3_-1731372392_Russian"
      },
      {
        "author": "LMB Studio",
        "link_thumb": "https://live.staticflickr.com/65535/51786435327_29e09aae43_o.gif",
        "link_bin": "https://github.com/lmbstudiocontact/mb5_25/raw/main/Shiv_L3_-1731372392_Spanish.bin",
        "name_language": "Spanish",
        "id_bin_language": "Shiv_L3_-1731372392_Spanish"
      }
    ],
    "array_tags": [
      "lmbstudio"
    ],
    "list_album": [
      {
        "id_album": "-568595356",
        "link_thumb": "https://live.staticflickr.com/65535/51786435612_b3923148ff_o.gif",
        "title": "Shiv_L3"
      }
    ]
  },
  {
    "author": "LMB Studio",
    "link_thumb": "https://live.staticflickr.com/65535/51787252661_3aa2f61708_o.gif",
    "link_bin": "https://github.com/lmbstudiocontact/mb5_25/raw/main/Shiv_L3_-1861554961.bin",
    "id_bin": "Shiv_L3_-1861554961",
    "list_language": [
      {
        "author": "LMB Studio",
        "link_thumb": "https://live.staticflickr.com/65535/51787875644_6dda8b2e68_o.gif",
        "link_bin": "https://github.com/lmbstudiocontact/mb5_25/raw/main/Shiv_L3_-1861554961_English.bin",
        "name_language": "English",
        "id_bin_language": "Shiv_L3_-1861554961_English"
      },
      {
        "author": "LMB Studio",
        "link_thumb": "https://live.staticflickr.com/65535/51787502723_e8de92d8a0_o.gif",
        "link_bin": "https://github.com/lmbstudiocontact/mb5_25/raw/main/Shiv_L3_-1861554961_Portuguese.bin",
        "name_language": "Portuguese",
        "id_bin_language": "Shiv_L3_-1861554961_Portuguese"
      },
      {
        "author": "LMB Studio",
        "link_thumb": "https://live.staticflickr.com/65535/51786434837_504b2661cf_o.gif",
        "link_bin": "https://github.com/lmbstudiocontact/mb5_25/raw/main/Shiv_L3_-1861554961_Russian.bin",
        "name_language": "Russian",
        "id_bin_language": "Shiv_L3_-1861554961_Russian"
      },
      {
        "author": "LMB Studio",
        "link_thumb": "https://live.staticflickr.com/65535/51787252436_1cdf83ed8a_o.gif",
        "link_bin": "https://github.com/lmbstudiocontact/mb5_25/raw/main/Shiv_L3_-1861554961_Spanish.bin",
        "name_language": "Spanish",
        "id_bin_language": "Shiv_L3_-1861554961_Spanish"
      }
    ],
    "array_tags": [
      "lmbstudio"
    ],
    "list_album": [
      {
        "id_album": "-568595356",
        "link_thumb": "https://live.staticflickr.com/65535/51787252661_3aa2f61708_o.gif",
        "title": "Shiv_L3"
      }
    ]
  },
  {
    "author": "LMB Studio",
    "link_thumb": "https://live.staticflickr.com/65535/51788123655_d0c0a8d947_o.gif",
    "link_bin": "https://github.com/lmbstudiocontact/mb5_25/raw/main/Shiv_L3_-2003148904.bin",
    "id_bin": "Shiv_L3_-2003148904",
    "list_language": [
      {
        "author": "LMB Studio",
        "link_thumb": "https://live.staticflickr.com/65535/51787252021_26118bf36e_o.gif",
        "link_bin": "https://github.com/lmbstudiocontact/mb5_25/raw/main/Shiv_L3_-2003148904_English.bin",
        "name_language": "English",
        "id_bin_language": "Shiv_L3_-2003148904_English"
      },
      {
        "author": "LMB Studio",
        "link_thumb": "https://live.staticflickr.com/65535/51787251971_e87a2c1a04_o.gif",
        "link_bin": "https://github.com/lmbstudiocontact/mb5_25/raw/main/Shiv_L3_-2003148904_Portuguese.bin",
        "name_language": "Portuguese",
        "id_bin_language": "Shiv_L3_-2003148904_Portuguese"
      },
      {
        "author": "LMB Studio",
        "link_thumb": "https://live.staticflickr.com/65535/51788123440_6d9c4650fd_o.gif",
        "link_bin": "https://github.com/lmbstudiocontact/mb5_25/raw/main/Shiv_L3_-2003148904_Russian.bin",
        "name_language": "Russian",
        "id_bin_language": "Shiv_L3_-2003148904_Russian"
      },
      {
        "author": "LMB Studio",
        "link_thumb": "https://live.staticflickr.com/65535/51787502038_318f29a6db_o.gif",
        "link_bin": "https://github.com/lmbstudiocontact/mb5_25/raw/main/Shiv_L3_-2003148904_Spanish.bin",
        "name_language": "Spanish",
        "id_bin_language": "Shiv_L3_-2003148904_Spanish"
      }
    ],
    "array_tags": [
      "lmbstudio"
    ],
    "list_album": [
      {
        "id_album": "-568595356",
        "link_thumb": "https://live.staticflickr.com/65535/51788123655_d0c0a8d947_o.gif",
        "title": "Shiv_L3"
      }
    ]
  },
  {
    "author": "LMB Studio",
    "link_thumb": "https://live.staticflickr.com/65535/51787882444_03558c90ed_o.gif",
    "link_bin": "https://github.com/lmbstudiocontact/mb5_25/raw/main/Shiv_L3_-370115709.bin",
    "id_bin": "Shiv_L3_-370115709",
    "list_language": [
      {
        "author": "LMB Studio",
        "link_thumb": "https://live.staticflickr.com/65535/51787509638_43be76b56b_o.gif",
        "link_bin": "https://github.com/lmbstudiocontact/mb5_25/raw/main/Shiv_L3_-370115709_English.bin",
        "name_language": "English",
        "id_bin_language": "Shiv_L3_-370115709_English"
      },
      {
        "author": "LMB Studio",
        "link_thumb": "https://live.staticflickr.com/65535/51787882364_6849e8ef37_o.gif",
        "link_bin": "https://github.com/lmbstudiocontact/mb5_25/raw/main/Shiv_L3_-370115709_Portuguese.bin",
        "name_language": "Portuguese",
        "id_bin_language": "Shiv_L3_-370115709_Portuguese"
      },
      {
        "author": "LMB Studio",
        "link_thumb": "https://live.staticflickr.com/65535/51787882309_e600c8f97e_o.gif",
        "link_bin": "https://github.com/lmbstudiocontact/mb5_25/raw/main/Shiv_L3_-370115709_Russian.bin",
        "name_language": "Russian",
        "id_bin_language": "Shiv_L3_-370115709_Russian"
      },
      {
        "author": "LMB Studio",
        "link_thumb": "https://live.staticflickr.com/65535/51787259246_a7fdc8fbe9_o.gif",
        "link_bin": "https://github.com/lmbstudiocontact/mb5_25/raw/main/Shiv_L3_-370115709_Spanish.bin",
        "name_language": "Spanish",
        "id_bin_language": "Shiv_L3_-370115709_Spanish"
      }
    ],
    "array_tags": [
      "lmbstudio"
    ],
    "list_album": [
      {
        "id_album": "-568595356",
        "link_thumb": "https://live.staticflickr.com/65535/51787882444_03558c90ed_o.gif",
        "title": "Shiv_L3"
      }
    ]
  },
  {
    "author": "LMB Studio",
    "link_thumb": "https://live.staticflickr.com/65535/51788130080_d543aedbbb_o.gif",
    "link_bin": "https://github.com/lmbstudiocontact/mb5_25/raw/main/Shiv_L3_-723781104.bin",
    "id_bin": "Shiv_L3_-723781104",
    "list_language": [
      {
        "author": "LMB Studio",
        "link_thumb": "https://live.staticflickr.com/65535/51787258536_62e6fb6102_o.gif",
        "link_bin": "https://github.com/lmbstudiocontact/mb5_25/raw/main/Shiv_L3_-723781104_English.bin",
        "name_language": "English",
        "id_bin_language": "Shiv_L3_-723781104_English"
      },
      {
        "author": "LMB Studio",
        "link_thumb": "https://live.staticflickr.com/65535/51786441182_2b48c9bd0c_o.gif",
        "link_bin": "https://github.com/lmbstudiocontact/mb5_25/raw/main/Shiv_L3_-723781104_Portuguese.bin",
        "name_language": "Portuguese",
        "id_bin_language": "Shiv_L3_-723781104_Portuguese"
      },
      {
        "author": "LMB Studio",
        "link_thumb": "https://live.staticflickr.com/65535/51788129920_2155922876_o.gif",
        "link_bin": "https://github.com/lmbstudiocontact/mb5_25/raw/main/Shiv_L3_-723781104_Russian.bin",
        "name_language": "Russian",
        "id_bin_language": "Shiv_L3_-723781104_Russian"
      },
      {
        "author": "LMB Studio",
        "link_thumb": "https://live.staticflickr.com/65535/51786441067_ed779f45e7_o.gif",
        "link_bin": "https://github.com/lmbstudiocontact/mb5_25/raw/main/Shiv_L3_-723781104_Spanish.bin",
        "name_language": "Spanish",
        "id_bin_language": "Shiv_L3_-723781104_Spanish"
      }
    ],
    "array_tags": [
      "lmbstudio"
    ],
    "list_album": [
      {
        "id_album": "-568595356",
        "link_thumb": "https://live.staticflickr.com/65535/51788130080_d543aedbbb_o.gif",
        "title": "Shiv_L3"
      }
    ]
  },
  {
    "author": "LMB Studio",
    "link_thumb": "https://live.staticflickr.com/65535/51787507918_6646871231_o.gif",
    "link_bin": "https://github.com/lmbstudiocontact/mb5_25/raw/main/Shiv_L3_-788148427.bin",
    "id_bin": "Shiv_L3_-788148427",
    "list_language": [
      {
        "author": "LMB Studio",
        "link_thumb": "https://live.staticflickr.com/65535/51787880719_bbdea522a7_o.gif",
        "link_bin": "https://github.com/lmbstudiocontact/mb5_25/raw/main/Shiv_L3_-788148427_English.bin",
        "name_language": "English",
        "id_bin_language": "Shiv_L3_-788148427_English"
      },
      {
        "author": "LMB Studio",
        "link_thumb": "https://live.staticflickr.com/65535/51787257511_d14ac9c609_o.gif",
        "link_bin": "https://github.com/lmbstudiocontact/mb5_25/raw/main/Shiv_L3_-788148427_Portuguese.bin",
        "name_language": "Portuguese",
        "id_bin_language": "Shiv_L3_-788148427_Portuguese"
      },
      {
        "author": "LMB Studio",
        "link_thumb": "https://live.staticflickr.com/65535/51787507753_ee33f37869_o.gif",
        "link_bin": "https://github.com/lmbstudiocontact/mb5_25/raw/main/Shiv_L3_-788148427_Russian.bin",
        "name_language": "Russian",
        "id_bin_language": "Shiv_L3_-788148427_Russian"
      },
      {
        "author": "LMB Studio",
        "link_thumb": "https://live.staticflickr.com/65535/51787257416_e3346a581a_o.gif",
        "link_bin": "https://github.com/lmbstudiocontact/mb5_25/raw/main/Shiv_L3_-788148427_Spanish.bin",
        "name_language": "Spanish",
        "id_bin_language": "Shiv_L3_-788148427_Spanish"
      }
    ],
    "array_tags": [
      "lmbstudio"
    ],
    "list_album": [
      {
        "id_album": "-568595356",
        "link_thumb": "https://live.staticflickr.com/65535/51787507918_6646871231_o.gif",
        "title": "Shiv_L3"
      }
    ]
  },
  {
    "author": "LMB Studio",
    "link_thumb": "https://live.staticflickr.com/65535/51787507648_f17958e038_o.gif",
    "link_bin": "https://github.com/lmbstudiocontact/mb5_25/raw/main/Shiv_L3_-931001208.bin",
    "id_bin": "Shiv_L3_-931001208",
    "list_language": [
      {
        "author": "LMB Studio",
        "link_thumb": "https://live.staticflickr.com/65535/51788128850_2422f29a72_o.gif",
        "link_bin": "https://github.com/lmbstudiocontact/mb5_26/raw/main/Shiv_L3_-931001208_English.bin",
        "name_language": "English",
        "id_bin_language": "Shiv_L3_-931001208_English"
      },
      {
        "author": "LMB Studio",
        "link_thumb": "https://live.staticflickr.com/65535/51787880394_2d752ac716_o.gif",
        "link_bin": "https://github.com/lmbstudiocontact/mb5_26/raw/main/Shiv_L3_-931001208_Portuguese.bin",
        "name_language": "Portuguese",
        "id_bin_language": "Shiv_L3_-931001208_Portuguese"
      },
      {
        "author": "LMB Studio",
        "link_thumb": "https://live.staticflickr.com/65535/51787880334_55839bcc83_o.gif",
        "link_bin": "https://github.com/lmbstudiocontact/mb5_26/raw/main/Shiv_L3_-931001208_Russian.bin",
        "name_language": "Russian",
        "id_bin_language": "Shiv_L3_-931001208_Russian"
      },
      {
        "author": "LMB Studio",
        "link_thumb": "https://live.staticflickr.com/65535/51787880284_d422c5b415_o.gif",
        "link_bin": "https://github.com/lmbstudiocontact/mb5_26/raw/main/Shiv_L3_-931001208_Spanish.bin",
        "name_language": "Spanish",
        "id_bin_language": "Shiv_L3_-931001208_Spanish"
      }
    ],
    "array_tags": [
      "lmbstudio"
    ],
    "list_album": [
      {
        "id_album": "-568595356",
        "link_thumb": "https://live.staticflickr.com/65535/51787507648_f17958e038_o.gif",
        "title": "Shiv_L3"
      }
    ]
  },
  {
    "author": "LMB Studio",
    "link_thumb": "https://live.staticflickr.com/65535/51787507368_526b110a57_o.gif",
    "link_bin": "https://github.com/lmbstudiocontact/mb5_26/raw/main/Shiv_L3_-958643350.bin",
    "id_bin": "Shiv_L3_-958643350",
    "list_language": [
      {
        "author": "LMB Studio",
        "link_thumb": "https://live.staticflickr.com/65535/51787507278_14c7c74f6a_o.gif",
        "link_bin": "https://github.com/lmbstudiocontact/mb5_26/raw/main/Shiv_L3_-958643350_English.bin",
        "name_language": "English",
        "id_bin_language": "Shiv_L3_-958643350_English"
      },
      {
        "author": "LMB Studio",
        "link_thumb": "https://live.staticflickr.com/65535/51787880139_6c9b30f994_o.gif",
        "link_bin": "https://github.com/lmbstudiocontact/mb5_26/raw/main/Shiv_L3_-958643350_Portuguese.bin",
        "name_language": "Portuguese",
        "id_bin_language": "Shiv_L3_-958643350_Portuguese"
      },
      {
        "author": "LMB Studio",
        "link_thumb": "https://live.staticflickr.com/65535/51787256936_09a756c883_o.gif",
        "link_bin": "https://github.com/lmbstudiocontact/mb5_26/raw/main/Shiv_L3_-958643350_Russian.bin",
        "name_language": "Russian",
        "id_bin_language": "Shiv_L3_-958643350_Russian"
      },
      {
        "author": "LMB Studio",
        "link_thumb": "https://live.staticflickr.com/65535/51787507113_ce0acd8afc_o.gif",
        "link_bin": "https://github.com/lmbstudiocontact/mb5_26/raw/main/Shiv_L3_-958643350_Spanish.bin",
        "name_language": "Spanish",
        "id_bin_language": "Shiv_L3_-958643350_Spanish"
      }
    ],
    "array_tags": [
      "lmbstudio"
    ],
    "list_album": [
      {
        "id_album": "-568595356",
        "link_thumb": "https://live.staticflickr.com/65535/51787507368_526b110a57_o.gif",
        "title": "Shiv_L3"
      }
    ]
  },
  {
    "author": "LMB Studio",
    "link_thumb": "https://live.staticflickr.com/65535/51786439432_a63d03b079_o.gif",
    "link_bin": "https://github.com/lmbstudiocontact/mb5_26/raw/main/Shiv_L3_-983869570.bin",
    "id_bin": "Shiv_L3_-983869570",
    "list_language": [
      {
        "author": "LMB Studio",
        "link_thumb": "https://live.staticflickr.com/65535/51786439367_0560260961_o.gif",
        "link_bin": "https://github.com/lmbstudiocontact/mb5_26/raw/main/Shiv_L3_-983869570_English.bin",
        "name_language": "English",
        "id_bin_language": "Shiv_L3_-983869570_English"
      },
      {
        "author": "LMB Studio",
        "link_thumb": "https://live.staticflickr.com/65535/51786439347_13b443802d_o.gif",
        "link_bin": "https://github.com/lmbstudiocontact/mb5_26/raw/main/Shiv_L3_-983869570_Portuguese.bin",
        "name_language": "Portuguese",
        "id_bin_language": "Shiv_L3_-983869570_Portuguese"
      },
      {
        "author": "LMB Studio",
        "link_thumb": "https://live.staticflickr.com/65535/51786439292_9d5cc2b298_o.gif",
        "link_bin": "https://github.com/lmbstudiocontact/mb5_26/raw/main/Shiv_L3_-983869570_Russian.bin",
        "name_language": "Russian",
        "id_bin_language": "Shiv_L3_-983869570_Russian"
      },
      {
        "author": "LMB Studio",
        "link_thumb": "https://live.staticflickr.com/65535/51787256616_f990c4e7cd_o.gif",
        "link_bin": "https://github.com/lmbstudiocontact/mb5_26/raw/main/Shiv_L3_-983869570_Spanish.bin",
        "name_language": "Spanish",
        "id_bin_language": "Shiv_L3_-983869570_Spanish"
      }
    ],
    "array_tags": [
      "lmbstudio"
    ],
    "list_album": [
      {
        "id_album": "-568595356",
        "link_thumb": "https://live.staticflickr.com/65535/51786439432_a63d03b079_o.gif",
        "title": "Shiv_L3"
      }
    ]
  },
  {
    "author": "LMB Studio",
    "link_thumb": "https://live.staticflickr.com/65535/51787506168_84aeb80493_o.gif",
    "link_bin": "https://github.com/lmbstudiocontact/mb5_26/raw/main/Shiv_L3_1206963472.bin",
    "id_bin": "Shiv_L3_1206963472",
    "list_language": [
      {
        "author": "LMB Studio",
        "link_thumb": "https://live.staticflickr.com/65535/51787879079_f49cfa0ba2_o.gif",
        "link_bin": "https://github.com/lmbstudiocontact/mb5_26/raw/main/Shiv_L3_1206963472_English.bin",
        "name_language": "English",
        "id_bin_language": "Shiv_L3_1206963472_English"
      },
      {
        "author": "LMB Studio",
        "link_thumb": "https://live.staticflickr.com/65535/51787878979_00dfc80200_o.gif",
        "link_bin": "https://github.com/lmbstudiocontact/mb5_26/raw/main/Shiv_L3_1206963472_Portuguese.bin",
        "name_language": "Portuguese",
        "id_bin_language": "Shiv_L3_1206963472_Portuguese"
      },
      {
        "author": "LMB Studio",
        "link_thumb": "https://live.staticflickr.com/65535/51786438357_ae40364dce_o.gif",
        "link_bin": "https://github.com/lmbstudiocontact/mb5_26/raw/main/Shiv_L3_1206963472_Russian.bin",
        "name_language": "Russian",
        "id_bin_language": "Shiv_L3_1206963472_Russian"
      },
      {
        "author": "LMB Studio",
        "link_thumb": "https://live.staticflickr.com/65535/51786438297_948b31d214_o.gif",
        "link_bin": "https://github.com/lmbstudiocontact/mb5_26/raw/main/Shiv_L3_1206963472_Spanish.bin",
        "name_language": "Spanish",
        "id_bin_language": "Shiv_L3_1206963472_Spanish"
      }
    ],
    "array_tags": [
      "lmbstudio"
    ],
    "list_album": [
      {
        "id_album": "-568595356",
        "link_thumb": "https://live.staticflickr.com/65535/51787506168_84aeb80493_o.gif",
        "title": "Shiv_L3"
      }
    ]
  },
  {
    "author": "LMB Studio",
    "link_thumb": "https://live.staticflickr.com/65535/51786437532_84d423b310_o.gif",
    "link_bin": "https://github.com/lmbstudiocontact/mb5_26/raw/main/Shiv_L3_1383161369.bin",
    "id_bin": "Shiv_L3_1383161369",
    "list_language": [
      {
        "author": "LMB Studio",
        "link_thumb": "https://live.staticflickr.com/65535/51787878249_0afc99819e_o.gif",
        "link_bin": "https://github.com/lmbstudiocontact/mb5_26/raw/main/Shiv_L3_1383161369_English.bin",
        "name_language": "English",
        "id_bin_language": "Shiv_L3_1383161369_English"
      },
      {
        "author": "LMB Studio",
        "link_thumb": "https://live.staticflickr.com/65535/51787505098_a6079a292d_o.gif",
        "link_bin": "https://github.com/lmbstudiocontact/mb5_26/raw/main/Shiv_L3_1383161369_Portuguese.bin",
        "name_language": "Portuguese",
        "id_bin_language": "Shiv_L3_1383161369_Portuguese"
      },
      {
        "author": "LMB Studio",
        "link_thumb": "https://live.staticflickr.com/65535/51787254806_68bde9713b_o.gif",
        "link_bin": "https://github.com/lmbstudiocontact/mb5_26/raw/main/Shiv_L3_1383161369_Russian.bin",
        "name_language": "Russian",
        "id_bin_language": "Shiv_L3_1383161369_Russian"
      },
      {
        "author": "LMB Studio",
        "link_thumb": "https://live.staticflickr.com/65535/51787504993_abbe4f27c2_o.gif",
        "link_bin": "https://github.com/lmbstudiocontact/mb5_26/raw/main/Shiv_L3_1383161369_Spanish.bin",
        "name_language": "Spanish",
        "id_bin_language": "Shiv_L3_1383161369_Spanish"
      }
    ],
    "array_tags": [
      "lmbstudio"
    ],
    "list_album": [
      {
        "id_album": "-568595356",
        "link_thumb": "https://live.staticflickr.com/65535/51786437532_84d423b310_o.gif",
        "title": "Shiv_L3"
      }
    ]
  },
  {
    "author": "LMB Studio",
    "link_thumb": "https://live.staticflickr.com/65535/51788126455_9d3eb3df06_o.gif",
    "link_bin": "https://github.com/lmbstudiocontact/mb5_26/raw/main/Shiv_L3_1561380822.bin",
    "id_bin": "Shiv_L3_1561380822",
    "list_language": [
      {
        "author": "LMB Studio",
        "link_thumb": "https://live.staticflickr.com/65535/51787877859_c40fafb508_o.gif",
        "link_bin": "https://github.com/lmbstudiocontact/mb5_26/raw/main/Shiv_L3_1561380822_English.bin",
        "name_language": "English",
        "id_bin_language": "Shiv_L3_1561380822_English"
      },
      {
        "author": "LMB Studio",
        "link_thumb": "https://live.staticflickr.com/65535/51786437032_ece323cedd_o.gif",
        "link_bin": "https://github.com/lmbstudiocontact/mb5_26/raw/main/Shiv_L3_1561380822_Portuguese.bin",
        "name_language": "Portuguese",
        "id_bin_language": "Shiv_L3_1561380822_Portuguese"
      },
      {
        "author": "LMB Studio",
        "link_thumb": "https://live.staticflickr.com/65535/51788126270_74b4910bee_o.gif",
        "link_bin": "https://github.com/lmbstudiocontact/mb5_26/raw/main/Shiv_L3_1561380822_Russian.bin",
        "name_language": "Russian",
        "id_bin_language": "Shiv_L3_1561380822_Russian"
      },
      {
        "author": "LMB Studio",
        "link_thumb": "https://live.staticflickr.com/65535/51788126190_34b0f86f8a_o.gif",
        "link_bin": "https://github.com/lmbstudiocontact/mb5_26/raw/main/Shiv_L3_1561380822_Spanish.bin",
        "name_language": "Spanish",
        "id_bin_language": "Shiv_L3_1561380822_Spanish"
      }
    ],
    "array_tags": [
      "lmbstudio"
    ],
    "list_album": [
      {
        "id_album": "-568595356",
        "link_thumb": "https://live.staticflickr.com/65535/51788126455_9d3eb3df06_o.gif",
        "title": "Shiv_L3"
      }
    ]
  },
  {
    "author": "LMB Studio",
    "link_thumb": "https://live.staticflickr.com/65535/51787254106_ef5669915e_o.gif",
    "link_bin": "https://github.com/lmbstudiocontact/mb5_26/raw/main/Shiv_L3_1707684052.bin",
    "id_bin": "Shiv_L3_1707684052",
    "list_language": [
      {
        "author": "LMB Studio",
        "link_thumb": "https://live.staticflickr.com/65535/51786436482_a68fbd2502_o.gif",
        "link_bin": "https://github.com/lmbstudiocontact/mb5_26/raw/main/Shiv_L3_1707684052_English.bin",
        "name_language": "English",
        "id_bin_language": "Shiv_L3_1707684052_English"
      },
      {
        "author": "LMB Studio",
        "link_thumb": "https://live.staticflickr.com/65535/51787504273_cba1ecb6aa_o.gif",
        "link_bin": "https://github.com/lmbstudiocontact/mb5_26/raw/main/Shiv_L3_1707684052_Portuguese.bin",
        "name_language": "Portuguese",
        "id_bin_language": "Shiv_L3_1707684052_Portuguese"
      },
      {
        "author": "LMB Studio",
        "link_thumb": "https://live.staticflickr.com/65535/51787877174_d6514ee455_o.gif",
        "link_bin": "https://github.com/lmbstudiocontact/mb5_26/raw/main/Shiv_L3_1707684052_Russian.bin",
        "name_language": "Russian",
        "id_bin_language": "Shiv_L3_1707684052_Russian"
      },
      {
        "author": "LMB Studio",
        "link_thumb": "https://live.staticflickr.com/65535/51786436302_e06b431505_o.gif",
        "link_bin": "https://github.com/lmbstudiocontact/mb5_26/raw/main/Shiv_L3_1707684052_Spanish.bin",
        "name_language": "Spanish",
        "id_bin_language": "Shiv_L3_1707684052_Spanish"
      }
    ],
    "array_tags": [
      "lmbstudio"
    ],
    "list_album": [
      {
        "id_album": "-568595356",
        "link_thumb": "https://live.staticflickr.com/65535/51787254106_ef5669915e_o.gif",
        "title": "Shiv_L3"
      }
    ]
  },
  {
    "author": "LMB Studio",
    "link_thumb": "https://live.staticflickr.com/65535/51787877074_bab18eb39b_o.gif",
    "link_bin": "https://github.com/lmbstudiocontact/mb5_26/raw/main/Shiv_L3_1714571254.bin",
    "id_bin": "Shiv_L3_1714571254",
    "list_language": [
      {
        "author": "LMB Studio",
        "link_thumb": "https://live.staticflickr.com/65535/51786436252_b0cd9d4791_o.gif",
        "link_bin": "https://github.com/lmbstudiocontact/mb5_26/raw/main/Shiv_L3_1714571254_English.bin",
        "name_language": "English",
        "id_bin_language": "Shiv_L3_1714571254_English"
      },
      {
        "author": "LMB Studio",
        "link_thumb": "https://live.staticflickr.com/65535/51786436162_8b7a29111f_o.gif",
        "link_bin": "https://github.com/lmbstudiocontact/mb5_26/raw/main/Shiv_L3_1714571254_Portuguese.bin",
        "name_language": "Portuguese",
        "id_bin_language": "Shiv_L3_1714571254_Portuguese"
      },
      {
        "author": "LMB Studio",
        "link_thumb": "https://live.staticflickr.com/65535/51788125315_101a314162_o.gif",
        "link_bin": "https://github.com/lmbstudiocontact/mb5_26/raw/main/Shiv_L3_1714571254_Russian.bin",
        "name_language": "Russian",
        "id_bin_language": "Shiv_L3_1714571254_Russian"
      },
      {
        "author": "LMB Studio",
        "link_thumb": "https://live.staticflickr.com/65535/51788125270_f1120ebe87_o.gif",
        "link_bin": "https://github.com/lmbstudiocontact/mb5_26/raw/main/Shiv_L3_1714571254_Spanish.bin",
        "name_language": "Spanish",
        "id_bin_language": "Shiv_L3_1714571254_Spanish"
      }
    ],
    "array_tags": [
      "lmbstudio"
    ],
    "list_album": [
      {
        "id_album": "-568595356",
        "link_thumb": "https://live.staticflickr.com/65535/51787877074_bab18eb39b_o.gif",
        "title": "Shiv_L3"
      }
    ]
  },
  {
    "author": "LMB Studio",
    "link_thumb": "https://live.staticflickr.com/65535/51788124485_d5ef1d0ec4_o.gif",
    "link_bin": "https://github.com/lmbstudiocontact/mb5_26/raw/main/Shiv_L3_1759723990.bin",
    "id_bin": "Shiv_L3_1759723990",
    "list_language": [
      {
        "author": "LMB Studio",
        "link_thumb": "https://live.staticflickr.com/65535/51788124440_68ffec5905_o.gif",
        "link_bin": "https://github.com/lmbstudiocontact/mb5_26/raw/main/Shiv_L3_1759723990_English.bin",
        "name_language": "English",
        "id_bin_language": "Shiv_L3_1759723990_English"
      },
      {
        "author": "LMB Studio",
        "link_thumb": "https://live.staticflickr.com/65535/51788124365_657d48689a_o.gif",
        "link_bin": "https://github.com/lmbstudiocontact/mb5_26/raw/main/Shiv_L3_1759723990_Portuguese.bin",
        "name_language": "Portuguese",
        "id_bin_language": "Shiv_L3_1759723990_Portuguese"
      },
      {
        "author": "LMB Studio",
        "link_thumb": "https://live.staticflickr.com/65535/51787252766_1392cb1b2b_o.gif",
        "link_bin": "https://github.com/lmbstudiocontact/mb5_26/raw/main/Shiv_L3_1759723990_Russian.bin",
        "name_language": "Russian",
        "id_bin_language": "Shiv_L3_1759723990_Russian"
      },
      {
        "author": "LMB Studio",
        "link_thumb": "https://live.staticflickr.com/65535/51788124215_dc1e35d6de_o.gif",
        "link_bin": "https://github.com/lmbstudiocontact/mb5_26/raw/main/Shiv_L3_1759723990_Spanish.bin",
        "name_language": "Spanish",
        "id_bin_language": "Shiv_L3_1759723990_Spanish"
      }
    ],
    "array_tags": [
      "lmbstudio"
    ],
    "list_album": [
      {
        "id_album": "-568595356",
        "link_thumb": "https://live.staticflickr.com/65535/51788124485_d5ef1d0ec4_o.gif",
        "title": "Shiv_L3"
      }
    ]
  },
  {
    "author": "LMB Studio",
    "link_thumb": "https://live.staticflickr.com/65535/51787875389_4f95a5ddd4_o.gif",
    "link_bin": "https://github.com/lmbstudiocontact/mb5_26/raw/main/Shiv_L3_1923739490.bin",
    "id_bin": "Shiv_L3_1923739490",
    "list_language": [
      {
        "author": "LMB Studio",
        "link_thumb": "https://live.staticflickr.com/65535/51787502523_ea84e4e0d4_o.gif",
        "link_bin": "https://github.com/lmbstudiocontact/mb5_26/raw/main/Shiv_L3_1923739490_English.bin",
        "name_language": "English",
        "id_bin_language": "Shiv_L3_1923739490_English"
      },
      {
        "author": "LMB Studio",
        "link_thumb": "https://live.staticflickr.com/65535/51787252341_162fbb9109_o.gif",
        "link_bin": "https://github.com/lmbstudiocontact/mb5_26/raw/main/Shiv_L3_1923739490_Portuguese.bin",
        "name_language": "Portuguese",
        "id_bin_language": "Shiv_L3_1923739490_Portuguese"
      },
      {
        "author": "LMB Studio",
        "link_thumb": "https://live.staticflickr.com/65535/51787252251_db0e9c4811_o.gif",
        "link_bin": "https://github.com/lmbstudiocontact/mb5_26/raw/main/Shiv_L3_1923739490_Russian.bin",
        "name_language": "Russian",
        "id_bin_language": "Shiv_L3_1923739490_Russian"
      },
      {
        "author": "LMB Studio",
        "link_thumb": "https://live.staticflickr.com/65535/51786434572_ebb7e0210b_o.gif",
        "link_bin": "https://github.com/lmbstudiocontact/mb5_26/raw/main/Shiv_L3_1923739490_Spanish.bin",
        "name_language": "Spanish",
        "id_bin_language": "Shiv_L3_1923739490_Spanish"
      }
    ],
    "array_tags": [
      "lmbstudio"
    ],
    "list_album": [
      {
        "id_album": "-568595356",
        "link_thumb": "https://live.staticflickr.com/65535/51787875389_4f95a5ddd4_o.gif",
        "title": "Shiv_L3"
      }
    ]
  },
  {
    "author": "LMB Studio",
    "link_thumb": "https://live.staticflickr.com/65535/51788123335_d3921c3bce_o.gif",
    "link_bin": "https://github.com/lmbstudiocontact/mb5_26/raw/main/Shiv_L3_2060866981.bin",
    "id_bin": "Shiv_L3_2060866981",
    "list_language": [
      {
        "author": "LMB Studio",
        "link_thumb": "https://live.staticflickr.com/65535/51787874804_b85fd2e29d_o.gif",
        "link_bin": "https://github.com/lmbstudiocontact/mb5_26/raw/main/Shiv_L3_2060866981_English.bin",
        "name_language": "English",
        "id_bin_language": "Shiv_L3_2060866981_English"
      },
      {
        "author": "LMB Studio",
        "link_thumb": "https://live.staticflickr.com/65535/51787251671_5f06895229_o.gif",
        "link_bin": "https://github.com/lmbstudiocontact/mb5_26/raw/main/Shiv_L3_2060866981_Portuguese.bin",
        "name_language": "Portuguese",
        "id_bin_language": "Shiv_L3_2060866981_Portuguese"
      },
      {
        "author": "LMB Studio",
        "link_thumb": "https://live.staticflickr.com/65535/51787501803_dcb49146af_o.gif",
        "link_bin": "https://github.com/lmbstudiocontact/mb5_26/raw/main/Shiv_L3_2060866981_Russian.bin",
        "name_language": "Russian",
        "id_bin_language": "Shiv_L3_2060866981_Russian"
      },
      {
        "author": "LMB Studio",
        "link_thumb": "https://live.staticflickr.com/65535/51787251516_5556aa979d_o.gif",
        "link_bin": "https://github.com/lmbstudiocontact/mb5_26/raw/main/Shiv_L3_2060866981_Spanish.bin",
        "name_language": "Spanish",
        "id_bin_language": "Shiv_L3_2060866981_Spanish"
      }
    ],
    "array_tags": [
      "lmbstudio"
    ],
    "list_album": [
      {
        "id_album": "-568595356",
        "link_thumb": "https://live.staticflickr.com/65535/51788123335_d3921c3bce_o.gif",
        "title": "Shiv_L3"
      }
    ]
  },
  {
    "author": "LMB Studio",
    "link_thumb": "https://live.staticflickr.com/65535/51787874524_b48338808d_o.gif",
    "link_bin": "https://github.com/lmbstudiocontact/mb5_26/raw/main/Shiv_L3_2061589547.bin",
    "id_bin": "Shiv_L3_2061589547",
    "list_language": [
      {
        "author": "LMB Studio",
        "link_thumb": "https://live.staticflickr.com/65535/51787874479_fab273d02b_o.gif",
        "link_bin": "https://github.com/lmbstudiocontact/mb5_26/raw/main/Shiv_L3_2061589547_English.bin",
        "name_language": "English",
        "id_bin_language": "Shiv_L3_2061589547_English"
      },
      {
        "author": "LMB Studio",
        "link_thumb": "https://live.staticflickr.com/65535/51787251396_2f3edb50d2_o.gif",
        "link_bin": "https://github.com/lmbstudiocontact/mb5_26/raw/main/Shiv_L3_2061589547_Portuguese.bin",
        "name_language": "Portuguese",
        "id_bin_language": "Shiv_L3_2061589547_Portuguese"
      },
      {
        "author": "LMB Studio",
        "link_thumb": "https://live.staticflickr.com/65535/51787251351_694f4ee0a6_o.gif",
        "link_bin": "https://github.com/lmbstudiocontact/mb5_26/raw/main/Shiv_L3_2061589547_Russian.bin",
        "name_language": "Russian",
        "id_bin_language": "Shiv_L3_2061589547_Russian"
      },
      {
        "author": "LMB Studio",
        "link_thumb": "https://live.staticflickr.com/65535/51787501513_5a944b4da5_o.gif",
        "link_bin": "https://github.com/lmbstudiocontact/mb5_26/raw/main/Shiv_L3_2061589547_Spanish.bin",
        "name_language": "Spanish",
        "id_bin_language": "Shiv_L3_2061589547_Spanish"
      }
    ],
    "array_tags": [
      "lmbstudio"
    ],
    "list_album": [
      {
        "id_album": "-568595356",
        "link_thumb": "https://live.staticflickr.com/65535/51787874524_b48338808d_o.gif",
        "title": "Shiv_L3"
      }
    ]
  },
  {
    "author": "LMB Studio",
    "link_thumb": "https://live.staticflickr.com/65535/51788131100_d22d99bf54_o.gif",
    "link_bin": "https://github.com/lmbstudiocontact/mb5_26/raw/main/Shiv_L3_310632350.bin",
    "id_bin": "Shiv_L3_310632350",
    "list_language": [
      {
        "author": "LMB Studio",
        "link_thumb": "https://live.staticflickr.com/65535/51788131045_2f7d102788_o.gif",
        "link_bin": "https://github.com/lmbstudiocontact/mb5_26/raw/main/Shiv_L3_310632350_English.bin",
        "name_language": "English",
        "id_bin_language": "Shiv_L3_310632350_English"
      },
      {
        "author": "LMB Studio",
        "link_thumb": "https://live.staticflickr.com/65535/51787509953_4d5ae1d594_o.gif",
        "link_bin": "https://github.com/lmbstudiocontact/mb5_26/raw/main/Shiv_L3_310632350_Portuguese.bin",
        "name_language": "Portuguese",
        "id_bin_language": "Shiv_L3_310632350_Portuguese"
      },
      {
        "author": "LMB Studio",
        "link_thumb": "https://live.staticflickr.com/65535/51787882624_44cb2fcb26_o.gif",
        "link_bin": "https://github.com/lmbstudiocontact/mb5_26/raw/main/Shiv_L3_310632350_Russian.bin",
        "name_language": "Russian",
        "id_bin_language": "Shiv_L3_310632350_Russian"
      },
      {
        "author": "LMB Studio",
        "link_thumb": "https://live.staticflickr.com/65535/51787509773_fdf16ddbcc_o.gif",
        "link_bin": "https://github.com/lmbstudiocontact/mb5_26/raw/main/Shiv_L3_310632350_Spanish.bin",
        "name_language": "Spanish",
        "id_bin_language": "Shiv_L3_310632350_Spanish"
      }
    ],
    "array_tags": [
      "lmbstudio"
    ],
    "list_album": [
      {
        "id_album": "-568595356",
        "link_thumb": "https://live.staticflickr.com/65535/51788131100_d22d99bf54_o.gif",
        "title": "Shiv_L3"
      }
    ]
  },
  {
    "author": "LMB Studio",
    "link_thumb": "https://live.staticflickr.com/65535/51787509443_0600cb7be1_o.gif",
    "link_bin": "https://github.com/lmbstudiocontact/mb5_26/raw/main/Shiv_L3_426896343.bin",
    "id_bin": "Shiv_L3_426896343",
    "list_language": [
      {
        "author": "LMB Studio",
        "link_thumb": "https://live.staticflickr.com/65535/51787259171_d5c3e51eb8_o.gif",
        "link_bin": "https://github.com/lmbstudiocontact/mb5_26/raw/main/Shiv_L3_426896343_English.bin",
        "name_language": "English",
        "id_bin_language": "Shiv_L3_426896343_English"
      },
      {
        "author": "LMB Studio",
        "link_thumb": "https://live.staticflickr.com/65535/51787259141_cc7c9fd789_o.gif",
        "link_bin": "https://github.com/lmbstudiocontact/mb5_26/raw/main/Shiv_L3_426896343_Portuguese.bin",
        "name_language": "Portuguese",
        "id_bin_language": "Shiv_L3_426896343_Portuguese"
      },
      {
        "author": "LMB Studio",
        "link_thumb": "https://live.staticflickr.com/65535/51787509303_a72a0602b5_o.gif",
        "link_bin": "https://github.com/lmbstudiocontact/mb5_26/raw/main/Shiv_L3_426896343_Russian.bin",
        "name_language": "Russian",
        "id_bin_language": "Shiv_L3_426896343_Russian"
      },
      {
        "author": "LMB Studio",
        "link_thumb": "https://live.staticflickr.com/65535/51786441692_ec8ca06739_o.gif",
        "link_bin": "https://github.com/lmbstudiocontact/mb5_26/raw/main/Shiv_L3_426896343_Spanish.bin",
        "name_language": "Spanish",
        "id_bin_language": "Shiv_L3_426896343_Spanish"
      }
    ],
    "array_tags": [
      "lmbstudio"
    ],
    "list_album": [
      {
        "id_album": "-568595356",
        "link_thumb": "https://live.staticflickr.com/65535/51787509443_0600cb7be1_o.gif",
        "title": "Shiv_L3"
      }
    ]
  },
  {
    "author": "LMB Studio",
    "link_thumb": "https://live.staticflickr.com/65535/51788130325_820c95d037_o.gif",
    "link_bin": "https://github.com/lmbstudiocontact/mb5_26/raw/main/Shiv_L3_597123614.bin",
    "id_bin": "Shiv_L3_597123614",
    "list_language": [
      {
        "author": "LMB Studio",
        "link_thumb": "https://live.staticflickr.com/65535/51787881859_42124af5e9_o.gif",
        "link_bin": "https://github.com/lmbstudiocontact/mb5_26/raw/main/Shiv_L3_597123614_English.bin",
        "name_language": "English",
        "id_bin_language": "Shiv_L3_597123614_English"
      },
      {
        "author": "LMB Studio",
        "link_thumb": "https://live.staticflickr.com/65535/51787258831_be059b2bd9_o.gif",
        "link_bin": "https://github.com/lmbstudiocontact/mb5_26/raw/main/Shiv_L3_597123614_Portuguese.bin",
        "name_language": "Portuguese",
        "id_bin_language": "Shiv_L3_597123614_Portuguese"
      },
      {
        "author": "LMB Studio",
        "link_thumb": "https://live.staticflickr.com/65535/51786441462_3972671cef_o.gif",
        "link_bin": "https://github.com/lmbstudiocontact/mb5_26/raw/main/Shiv_L3_597123614_Russian.bin",
        "name_language": "Russian",
        "id_bin_language": "Shiv_L3_597123614_Russian"
      },
      {
        "author": "LMB Studio",
        "link_thumb": "https://live.staticflickr.com/65535/51787258711_54d3d15772_o.gif",
        "link_bin": "https://github.com/lmbstudiocontact/mb5_26/raw/main/Shiv_L3_597123614_Spanish.bin",
        "name_language": "Spanish",
        "id_bin_language": "Shiv_L3_597123614_Spanish"
      }
    ],
    "array_tags": [
      "lmbstudio"
    ],
    "list_album": [
      {
        "id_album": "-568595356",
        "link_thumb": "https://live.staticflickr.com/65535/51788130325_820c95d037_o.gif",
        "title": "Shiv_L3"
      }
    ]
  },
  {
    "author": "LMB Studio",
    "link_thumb": "https://live.staticflickr.com/65535/51788129795_ba1822272c_o.gif",
    "link_bin": "https://github.com/lmbstudiocontact/mb5_26/raw/main/Shiv_L3_728754260.bin",
    "id_bin": "Shiv_L3_728754260",
    "list_language": [
      {
        "author": "LMB Studio",
        "link_thumb": "https://live.staticflickr.com/65535/51787258221_02873bcc50_o.gif",
        "link_bin": "https://github.com/lmbstudiocontact/mb5_26/raw/main/Shiv_L3_728754260_English.bin",
        "name_language": "English",
        "id_bin_language": "Shiv_L3_728754260_English"
      },
      {
        "author": "LMB Studio",
        "link_thumb": "https://live.staticflickr.com/65535/51787508443_a9485b0845_o.gif",
        "link_bin": "https://github.com/lmbstudiocontact/mb5_26/raw/main/Shiv_L3_728754260_Portuguese.bin",
        "name_language": "Portuguese",
        "id_bin_language": "Shiv_L3_728754260_Portuguese"
      },
      {
        "author": "LMB Studio",
        "link_thumb": "https://live.staticflickr.com/65535/51787881274_8fc5347a23_o.gif",
        "link_bin": "https://github.com/lmbstudiocontact/mb5_26/raw/main/Shiv_L3_728754260_Russian.bin",
        "name_language": "Russian",
        "id_bin_language": "Shiv_L3_728754260_Russian"
      },
      {
        "author": "LMB Studio",
        "link_thumb": "https://live.staticflickr.com/65535/51787258061_1be519b4df_o.gif",
        "link_bin": "https://github.com/lmbstudiocontact/mb5_26/raw/main/Shiv_L3_728754260_Spanish.bin",
        "name_language": "Spanish",
        "id_bin_language": "Shiv_L3_728754260_Spanish"
      }
    ],
    "array_tags": [
      "lmbstudio"
    ],
    "list_album": [
      {
        "id_album": "-568595356",
        "link_thumb": "https://live.staticflickr.com/65535/51788129795_ba1822272c_o.gif",
        "title": "Shiv_L3"
      }
    ]
  },
  {
    "author": "LMB Studio",
    "link_thumb": "https://live.staticflickr.com/65535/51787881204_02e856c0f9_o.gif",
    "link_bin": "https://github.com/lmbstudiocontact/mb5_26/raw/main/Shiv_L3_758912854.bin",
    "id_bin": "Shiv_L3_758912854",
    "list_language": [
      {
        "author": "LMB Studio",
        "link_thumb": "https://live.staticflickr.com/65535/51786440717_01f1298fec_o.gif",
        "link_bin": "https://github.com/lmbstudiocontact/mb5_26/raw/main/Shiv_L3_758912854_English.bin",
        "name_language": "English",
        "id_bin_language": "Shiv_L3_758912854_English"
      },
      {
        "author": "LMB Studio",
        "link_thumb": "https://live.staticflickr.com/65535/51788129475_15bc2d174e_o.gif",
        "link_bin": "https://github.com/lmbstudiocontact/mb5_26/raw/main/Shiv_L3_758912854_Portuguese.bin",
        "name_language": "Portuguese",
        "id_bin_language": "Shiv_L3_758912854_Portuguese"
      },
      {
        "author": "LMB Studio",
        "link_thumb": "https://live.staticflickr.com/65535/51787881039_32d3f01db9_o.gif",
        "link_bin": "https://github.com/lmbstudiocontact/mb5_26/raw/main/Shiv_L3_758912854_Russian.bin",
        "name_language": "Russian",
        "id_bin_language": "Shiv_L3_758912854_Russian"
      },
      {
        "author": "LMB Studio",
        "link_thumb": "https://live.staticflickr.com/65535/51786440557_17feafaecd_o.gif",
        "link_bin": "https://github.com/lmbstudiocontact/mb5_26/raw/main/Shiv_L3_758912854_Spanish.bin",
        "name_language": "Spanish",
        "id_bin_language": "Shiv_L3_758912854_Spanish"
      }
    ],
    "array_tags": [
      "lmbstudio"
    ],
    "list_album": [
      {
        "id_album": "-568595356",
        "link_thumb": "https://live.staticflickr.com/65535/51787881204_02e856c0f9_o.gif",
        "title": "Shiv_L3"
      }
    ]
  },
  {
    "author": "LMB Studio",
    "link_thumb": "https://live.staticflickr.com/65535/51786440537_b840b8d13c_o.gif",
    "link_bin": "https://github.com/lmbstudiocontact/mb5_26/raw/main/Shiv_L3_762517339.bin",
    "id_bin": "Shiv_L3_762517339",
    "list_language": [
      {
        "author": "LMB Studio",
        "link_thumb": "https://live.staticflickr.com/65535/51787508048_f3ef3480cb_o.gif",
        "link_bin": "https://github.com/lmbstudiocontact/mb5_26/raw/main/Shiv_L3_762517339_English.bin",
        "name_language": "English",
        "id_bin_language": "Shiv_L3_762517339_English"
      },
      {
        "author": "LMB Studio",
        "link_thumb": "https://live.staticflickr.com/65535/51787880864_637676242d_o.gif",
        "link_bin": "https://github.com/lmbstudiocontact/mb5_26/raw/main/Shiv_L3_762517339_Portuguese.bin",
        "name_language": "Portuguese",
        "id_bin_language": "Shiv_L3_762517339_Portuguese"
      },
      {
        "author": "LMB Studio",
        "link_thumb": "https://live.staticflickr.com/65535/51787880834_5548220927_o.gif",
        "link_bin": "https://github.com/lmbstudiocontact/mb5_26/raw/main/Shiv_L3_762517339_Russian.bin",
        "name_language": "Russian",
        "id_bin_language": "Shiv_L3_762517339_Russian"
      },
      {
        "author": "LMB Studio",
        "link_thumb": "https://live.staticflickr.com/65535/51787507943_9f72ae6d4b_o.gif",
        "link_bin": "https://github.com/lmbstudiocontact/mb5_26/raw/main/Shiv_L3_762517339_Spanish.bin",
        "name_language": "Spanish",
        "id_bin_language": "Shiv_L3_762517339_Spanish"
      }
    ],
    "array_tags": [
      "lmbstudio"
    ],
    "list_album": [
      {
        "id_album": "-568595356",
        "link_thumb": "https://live.staticflickr.com/65535/51786440537_b840b8d13c_o.gif",
        "title": "Shiv_L3"
      }
    ]
  },
  {
    "author": "LMB Studio",
    "link_thumb": "https://live.staticflickr.com/65535/51787510473_efeb04981a_o.gif",
    "link_bin": "https://github.com/lmbstudiocontact/mb5_26/raw/main/Shiv_L3_82450228.bin",
    "id_bin": "Shiv_L3_82450228",
    "list_language": [
      {
        "author": "LMB Studio",
        "link_thumb": "https://live.staticflickr.com/65535/51787510428_2bcf9f1117_o.gif",
        "link_bin": "https://github.com/lmbstudiocontact/mb5_26/raw/main/Shiv_L3_82450228_English.bin",
        "name_language": "English",
        "id_bin_language": "Shiv_L3_82450228_English"
      },
      {
        "author": "LMB Studio",
        "link_thumb": "https://live.staticflickr.com/65535/51787260261_6b4e856897_o.gif",
        "link_bin": "https://github.com/lmbstudiocontact/mb5_26/raw/main/Shiv_L3_82450228_Portuguese.bin",
        "name_language": "Portuguese",
        "id_bin_language": "Shiv_L3_82450228_Portuguese"
      },
      {
        "author": "LMB Studio",
        "link_thumb": "https://live.staticflickr.com/65535/51788131435_5e1a0b009b_o.gif",
        "link_bin": "https://github.com/lmbstudiocontact/mb5_26/raw/main/Shiv_L3_82450228_Russian.bin",
        "name_language": "Russian",
        "id_bin_language": "Shiv_L3_82450228_Russian"
      },
      {
        "author": "LMB Studio",
        "link_thumb": "https://live.staticflickr.com/65535/51787510323_9f4fc9a170_o.gif",
        "link_bin": "https://github.com/lmbstudiocontact/mb5_26/raw/main/Shiv_L3_82450228_Spanish.bin",
        "name_language": "Spanish",
        "id_bin_language": "Shiv_L3_82450228_Spanish"
      }
    ],
    "array_tags": [
      "lmbstudio"
    ],
    "list_album": [
      {
        "id_album": "-568595356",
        "link_thumb": "https://live.staticflickr.com/65535/51787510473_efeb04981a_o.gif",
        "title": "Shiv_L3"
      }
    ]
  },
  {
    "author": "LMB Studio",
    "link_thumb": "https://live.staticflickr.com/65535/51786439182_d906ebcf6c_o.gif",
    "link_bin": "https://github.com/lmbstudiocontact/mb5_26/raw/main/Shiv_L3_990869478.bin",
    "id_bin": "Shiv_L3_990869478",
    "list_language": [
      {
        "author": "LMB Studio",
        "link_thumb": "https://live.staticflickr.com/65535/51787879654_70d54a3f6f_o.gif",
        "link_bin": "https://github.com/lmbstudiocontact/mb5_26/raw/main/Shiv_L3_990869478_English.bin",
        "name_language": "English",
        "id_bin_language": "Shiv_L3_990869478_English"
      },
      {
        "author": "LMB Studio",
        "link_thumb": "https://live.staticflickr.com/65535/51787256471_9318211423_o.gif",
        "link_bin": "https://github.com/lmbstudiocontact/mb5_26/raw/main/Shiv_L3_990869478_Portuguese.bin",
        "name_language": "Portuguese",
        "id_bin_language": "Shiv_L3_990869478_Portuguese"
      },
      {
        "author": "LMB Studio",
        "link_thumb": "https://live.staticflickr.com/65535/51787879554_8e8b9a2b2f_o.gif",
        "link_bin": "https://github.com/lmbstudiocontact/mb5_26/raw/main/Shiv_L3_990869478_Russian.bin",
        "name_language": "Russian",
        "id_bin_language": "Shiv_L3_990869478_Russian"
      },
      {
        "author": "LMB Studio",
        "link_thumb": "https://live.staticflickr.com/65535/51787256371_35c34c9204_o.gif",
        "link_bin": "https://github.com/lmbstudiocontact/mb5_26/raw/main/Shiv_L3_990869478_Spanish.bin",
        "name_language": "Spanish",
        "id_bin_language": "Shiv_L3_990869478_Spanish"
      }
    ],
    "array_tags": [
      "lmbstudio"
    ],
    "list_album": [
      {
        "id_album": "-568595356",
        "link_thumb": "https://live.staticflickr.com/65535/51786439182_d906ebcf6c_o.gif",
        "title": "Shiv_L3"
      }
    ]
  }
]