[
  {
    "author": "LMB Studio",
    "link_thumb": "https://live.staticflickr.com/65535/51698186678_577af32621_o.gif",
    "link_bin": "https://github.com/lmbstudiocontact/mb5_33/raw/main/Frozen Cartoon_L5_-1032361589.bin",
    "id_bin": "Frozen Cartoon_L5_-1032361589",
    "list_language": [
      {
        "author": "LMB Studio",
        "link_thumb": "https://live.staticflickr.com/65535/51702526480_81e67510dc_o.gif",
        "link_bin": "https://github.com/lmbstudiocontact/mb5_33/raw/main/Frozen Cartoon_L5_-1032361589_English.bin",
        "name_language": "English",
        "id_bin_language": "Frozen Cartoon_L5_-1032361589_English"
      },
      {
        "author": "LMB Studio",
        "link_thumb": "https://live.staticflickr.com/65535/51697118692_322d3174f8_o.gif",
        "link_bin": "https://github.com/lmbstudiocontact/mb5_33/raw/main/Frozen Cartoon_L5_-1032361589_Portuguese.bin",
        "name_language": "Portuguese",
        "id_bin_language": "Frozen Cartoon_L5_-1032361589_Portuguese"
      },
      {
        "author": "LMB Studio",
        "link_thumb": "https://live.staticflickr.com/65535/51698590349_0f2bbe92cb_o.gif",
        "link_bin": "https://github.com/lmbstudiocontact/mb5_33/raw/main/Frozen Cartoon_L5_-1032361589_Russian.bin",
        "name_language": "Russian",
        "id_bin_language": "Frozen Cartoon_L5_-1032361589_Russian"
      },
      {
        "author": "LMB Studio",
        "link_thumb": "https://live.staticflickr.com/65535/51698590774_4a09e9cb23_o.gif",
        "link_bin": "https://github.com/lmbstudiocontact/mb5_33/raw/main/Frozen Cartoon_L5_-1032361589_Spanish.bin",
        "name_language": "Spanish",
        "id_bin_language": "Frozen Cartoon_L5_-1032361589_Spanish"
      }
    ],
    "array_tags": [
      "lmbstudio"
    ],
    "list_album": [
      {
        "id_album": "995274074",
        "link_thumb": "https://live.staticflickr.com/65535/51698186678_577af32621_o.gif",
        "title": "Frozen Cartoon_L5"
      }
    ]
  },
  {
    "author": "LMB Studio",
    "link_thumb": "https://live.staticflickr.com/65535/51698799055_32ed96da3a_o.gif",
    "link_bin": "https://github.com/lmbstudiocontact/mb5_33/raw/main/Frozen Cartoon_L5_-1626566353.bin",
    "id_bin": "Frozen Cartoon_L5_-1626566353",
    "list_language": [
      {
        "author": "LMB Studio",
        "link_thumb": "https://live.staticflickr.com/65535/51698190963_70d77c000e_o.gif",
        "link_bin": "https://github.com/lmbstudiocontact/mb5_33/raw/main/Frozen Cartoon_L5_-1626566353_English.bin",
        "name_language": "English",
        "id_bin_language": "Frozen Cartoon_L5_-1626566353_English"
      },
      {
        "author": "LMB Studio",
        "link_thumb": "https://live.staticflickr.com/65535/51698592299_1fa9d26780_o.gif",
        "link_bin": "https://github.com/lmbstudiocontact/mb5_33/raw/main/Frozen Cartoon_L5_-1626566353_Portuguese.bin",
        "name_language": "Portuguese",
        "id_bin_language": "Frozen Cartoon_L5_-1626566353_Portuguese"
      },
      {
        "author": "LMB Studio",
        "link_thumb": "https://live.staticflickr.com/65535/51697913806_1516742d52_o.gif",
        "link_bin": "https://github.com/lmbstudiocontact/mb5_33/raw/main/Frozen Cartoon_L5_-1626566353_Russian.bin",
        "name_language": "Russian",
        "id_bin_language": "Frozen Cartoon_L5_-1626566353_Russian"
      },
      {
        "author": "LMB Studio",
        "link_thumb": "https://live.staticflickr.com/65535/51697914356_cc0a608204_o.gif",
        "link_bin": "https://github.com/lmbstudiocontact/mb5_33/raw/main/Frozen Cartoon_L5_-1626566353_Spanish.bin",
        "name_language": "Spanish",
        "id_bin_language": "Frozen Cartoon_L5_-1626566353_Spanish"
      }
    ],
    "array_tags": [
      "lmbstudio"
    ],
    "list_album": [
      {
        "id_album": "995274074",
        "link_thumb": "https://live.staticflickr.com/65535/51698799055_32ed96da3a_o.gif",
        "title": "Frozen Cartoon_L5"
      }
    ]
  },
  {
    "author": "LMB Studio",
    "link_thumb": "https://live.staticflickr.com/65535/51697122662_b27163fd18_o.gif",
    "link_bin": "https://github.com/lmbstudiocontact/mb5_33/raw/main/Frozen Cartoon_L5_-1648700174.bin",
    "id_bin": "Frozen Cartoon_L5_-1648700174",
    "list_language": [
      {
        "author": "LMB Studio",
        "link_thumb": "https://live.staticflickr.com/65535/51697915276_2915aa812d_o.gif",
        "link_bin": "https://github.com/lmbstudiocontact/mb5_33/raw/main/Frozen Cartoon_L5_-1648700174_English.bin",
        "name_language": "English",
        "id_bin_language": "Frozen Cartoon_L5_-1648700174_English"
      },
      {
        "author": "LMB Studio",
        "link_thumb": "https://live.staticflickr.com/65535/51698193778_77fcf3289c_o.gif",
        "link_bin": "https://github.com/lmbstudiocontact/mb5_33/raw/main/Frozen Cartoon_L5_-1648700174_Portuguese.bin",
        "name_language": "Portuguese",
        "id_bin_language": "Frozen Cartoon_L5_-1648700174_Portuguese"
      },
      {
        "author": "LMB Studio",
        "link_thumb": "https://live.staticflickr.com/65535/51697916056_a7c1cfbc28_o.gif",
        "link_bin": "https://github.com/lmbstudiocontact/mb5_33/raw/main/Frozen Cartoon_L5_-1648700174_Russian.bin",
        "name_language": "Russian",
        "id_bin_language": "Frozen Cartoon_L5_-1648700174_Russian"
      },
      {
        "author": "LMB Studio",
        "link_thumb": "https://live.staticflickr.com/65535/51697124417_ef568953ea_o.gif",
        "link_bin": "https://github.com/lmbstudiocontact/mb5_33/raw/main/Frozen Cartoon_L5_-1648700174_Spanish.bin",
        "name_language": "Spanish",
        "id_bin_language": "Frozen Cartoon_L5_-1648700174_Spanish"
      }
    ],
    "array_tags": [
      "lmbstudio"
    ],
    "list_album": [
      {
        "id_album": "995274074",
        "link_thumb": "https://live.staticflickr.com/65535/51697122662_b27163fd18_o.gif",
        "title": "Frozen Cartoon_L5"
      }
    ]
  },
  {
    "author": "LMB Studio",
    "link_thumb": "https://live.staticflickr.com/65535/51698194873_7dbb206964_o.gif",
    "link_bin": "https://github.com/lmbstudiocontact/mb5_33/raw/main/Frozen Cartoon_L5_-1812435299.bin",
    "id_bin": "Frozen Cartoon_L5_-1812435299",
    "list_language": [
      {
        "author": "LMB Studio",
        "link_thumb": "https://live.staticflickr.com/65535/51698803805_1f3d12cf8f_o.gif",
        "link_bin": "https://github.com/lmbstudiocontact/mb5_33/raw/main/Frozen Cartoon_L5_-1812435299_English.bin",
        "name_language": "English",
        "id_bin_language": "Frozen Cartoon_L5_-1812435299_English"
      },
      {
        "author": "LMB Studio",
        "link_thumb": "https://live.staticflickr.com/65535/51698195768_a307a0dded_o.gif",
        "link_bin": "https://github.com/lmbstudiocontact/mb5_33/raw/main/Frozen Cartoon_L5_-1812435299_Portuguese.bin",
        "name_language": "Portuguese",
        "id_bin_language": "Frozen Cartoon_L5_-1812435299_Portuguese"
      },
      {
        "author": "LMB Studio",
        "link_thumb": "https://live.staticflickr.com/65535/51698597264_88ab466830_o.gif",
        "link_bin": "https://github.com/lmbstudiocontact/mb5_33/raw/main/Frozen Cartoon_L5_-1812435299_Russian.bin",
        "name_language": "Russian",
        "id_bin_language": "Frozen Cartoon_L5_-1812435299_Russian"
      },
      {
        "author": "LMB Studio",
        "link_thumb": "https://live.staticflickr.com/65535/51698196818_d912cac8fa_o.gif",
        "link_bin": "https://github.com/lmbstudiocontact/mb5_33/raw/main/Frozen Cartoon_L5_-1812435299_Spanish.bin",
        "name_language": "Spanish",
        "id_bin_language": "Frozen Cartoon_L5_-1812435299_Spanish"
      }
    ],
    "array_tags": [
      "lmbstudio"
    ],
    "list_album": [
      {
        "id_album": "995274074",
        "link_thumb": "https://live.staticflickr.com/65535/51698194873_7dbb206964_o.gif",
        "title": "Frozen Cartoon_L5"
      }
    ]
  },
  {
    "author": "LMB Studio",
    "link_thumb": "https://live.staticflickr.com/65535/51698197228_58057cef8a_o.gif",
    "link_bin": "https://github.com/lmbstudiocontact/mb5_33/raw/main/Frozen Cartoon_L5_1222168709.bin",
    "id_bin": "Frozen Cartoon_L5_1222168709",
    "list_language": [
      {
        "author": "LMB Studio",
        "link_thumb": "https://live.staticflickr.com/65535/51698805990_79a594866c_o.gif",
        "link_bin": "https://github.com/lmbstudiocontact/mb5_33/raw/main/Frozen Cartoon_L5_1222168709_English.bin",
        "name_language": "English",
        "id_bin_language": "Frozen Cartoon_L5_1222168709_English"
      },
      {
        "author": "LMB Studio",
        "link_thumb": "https://live.staticflickr.com/65535/51698598779_ef847385e8_o.gif",
        "link_bin": "https://github.com/lmbstudiocontact/mb5_33/raw/main/Frozen Cartoon_L5_1222168709_Portuguese.bin",
        "name_language": "Portuguese",
        "id_bin_language": "Frozen Cartoon_L5_1222168709_Portuguese"
      },
      {
        "author": "LMB Studio",
        "link_thumb": "https://live.staticflickr.com/65535/51698599074_afb347b6a3_o.gif",
        "link_bin": "https://github.com/lmbstudiocontact/mb5_33/raw/main/Frozen Cartoon_L5_1222168709_Russian.bin",
        "name_language": "Russian",
        "id_bin_language": "Frozen Cartoon_L5_1222168709_Russian"
      },
      {
        "author": "LMB Studio",
        "link_thumb": "https://live.staticflickr.com/65535/51698599474_da0c5f3831_o.gif",
        "link_bin": "https://github.com/lmbstudiocontact/mb5_33/raw/main/Frozen Cartoon_L5_1222168709_Spanish.bin",
        "name_language": "Spanish",
        "id_bin_language": "Frozen Cartoon_L5_1222168709_Spanish"
      }
    ],
    "array_tags": [
      "lmbstudio"
    ],
    "list_album": [
      {
        "id_album": "995274074",
        "link_thumb": "https://live.staticflickr.com/65535/51698197228_58057cef8a_o.gif",
        "title": "Frozen Cartoon_L5"
      }
    ]
  },
  {
    "author": "LMB Studio",
    "link_thumb": "https://live.staticflickr.com/65535/51697128797_cf27f79704_o.gif",
    "link_bin": "https://github.com/lmbstudiocontact/mb5_33/raw/main/Frozen Cartoon_L5_1264453491.bin",
    "id_bin": "Frozen Cartoon_L5_1264453491",
    "list_language": [
      {
        "author": "LMB Studio",
        "link_thumb": "https://live.staticflickr.com/65535/51698600239_fc68e3e930_o.gif",
        "link_bin": "https://github.com/lmbstudiocontact/mb5_33/raw/main/Frozen Cartoon_L5_1264453491_English.bin",
        "name_language": "English",
        "id_bin_language": "Frozen Cartoon_L5_1264453491_English"
      },
      {
        "author": "LMB Studio",
        "link_thumb": "https://live.staticflickr.com/65535/51698808210_133b84176e_o.gif",
        "link_bin": "https://github.com/lmbstudiocontact/mb5_33/raw/main/Frozen Cartoon_L5_1264453491_Portuguese.bin",
        "name_language": "Portuguese",
        "id_bin_language": "Frozen Cartoon_L5_1264453491_Portuguese"
      },
      {
        "author": "LMB Studio",
        "link_thumb": "https://live.staticflickr.com/65535/51698200223_bc8b8cf6c2_o.gif",
        "link_bin": "https://github.com/lmbstudiocontact/mb5_33/raw/main/Frozen Cartoon_L5_1264453491_Russian.bin",
        "name_language": "Russian",
        "id_bin_language": "Frozen Cartoon_L5_1264453491_Russian"
      },
      {
        "author": "LMB Studio",
        "link_thumb": "https://live.staticflickr.com/65535/51698809090_8c17cef5ce_o.gif",
        "link_bin": "https://github.com/lmbstudiocontact/mb5_33/raw/main/Frozen Cartoon_L5_1264453491_Spanish.bin",
        "name_language": "Spanish",
        "id_bin_language": "Frozen Cartoon_L5_1264453491_Spanish"
      }
    ],
    "array_tags": [
      "lmbstudio"
    ],
    "list_album": [
      {
        "id_album": "995274074",
        "link_thumb": "https://live.staticflickr.com/65535/51697128797_cf27f79704_o.gif",
        "title": "Frozen Cartoon_L5"
      }
    ]
  },
  {
    "author": "LMB Studio",
    "link_thumb": "https://live.staticflickr.com/65535/51697923106_bd889d0ebd_o.gif",
    "link_bin": "https://github.com/lmbstudiocontact/mb5_33/raw/main/Frozen Cartoon_L5_1330877434.bin",
    "id_bin": "Frozen Cartoon_L5_1330877434",
    "list_language": [
      {
        "author": "LMB Studio",
        "link_thumb": "https://live.staticflickr.com/65535/51698602239_d12613fa66_o.gif",
        "link_bin": "https://github.com/lmbstudiocontact/mb5_33/raw/main/Frozen Cartoon_L5_1330877434_English.bin",
        "name_language": "English",
        "id_bin_language": "Frozen Cartoon_L5_1330877434_English"
      },
      {
        "author": "LMB Studio",
        "link_thumb": "https://live.staticflickr.com/65535/51698602779_db0f39e284_o.gif",
        "link_bin": "https://github.com/lmbstudiocontact/mb5_33/raw/main/Frozen Cartoon_L5_1330877434_Portuguese.bin",
        "name_language": "Portuguese",
        "id_bin_language": "Frozen Cartoon_L5_1330877434_Portuguese"
      },
      {
        "author": "LMB Studio",
        "link_thumb": "https://live.staticflickr.com/65535/51698603304_c764d7f06a_o.gif",
        "link_bin": "https://github.com/lmbstudiocontact/mb5_33/raw/main/Frozen Cartoon_L5_1330877434_Russian.bin",
        "name_language": "Russian",
        "id_bin_language": "Frozen Cartoon_L5_1330877434_Russian"
      },
      {
        "author": "LMB Studio",
        "link_thumb": "https://live.staticflickr.com/65535/51698603574_c8b0570b84_o.gif",
        "link_bin": "https://github.com/lmbstudiocontact/mb5_33/raw/main/Frozen Cartoon_L5_1330877434_Spanish.bin",
        "name_language": "Spanish",
        "id_bin_language": "Frozen Cartoon_L5_1330877434_Spanish"
      }
    ],
    "array_tags": [
      "lmbstudio"
    ],
    "list_album": [
      {
        "id_album": "995274074",
        "link_thumb": "https://live.staticflickr.com/65535/51697923106_bd889d0ebd_o.gif",
        "title": "Frozen Cartoon_L5"
      }
    ]
  },
  {
    "author": "LMB Studio",
    "link_thumb": "https://live.staticflickr.com/65535/51697133377_c58343f90d_o.gif",
    "link_bin": "https://github.com/lmbstudiocontact/mb5_33/raw/main/Frozen Cartoon_L5_1529528592.bin",
    "id_bin": "Frozen Cartoon_L5_1529528592",
    "list_language": [
      {
        "author": "LMB Studio",
        "link_thumb": "https://live.staticflickr.com/65535/51697925391_5a7359d047_o.gif",
        "link_bin": "https://github.com/lmbstudiocontact/mb5_33/raw/main/Frozen Cartoon_L5_1529528592_English.bin",
        "name_language": "English",
        "id_bin_language": "Frozen Cartoon_L5_1529528592_English"
      },
      {
        "author": "LMB Studio",
        "link_thumb": "https://live.staticflickr.com/65535/51697133987_895584f078_o.gif",
        "link_bin": "https://github.com/lmbstudiocontact/mb5_33/raw/main/Frozen Cartoon_L5_1529528592_Portuguese.bin",
        "name_language": "Portuguese",
        "id_bin_language": "Frozen Cartoon_L5_1529528592_Portuguese"
      },
      {
        "author": "LMB Studio",
        "link_thumb": "https://live.staticflickr.com/65535/51697134352_5a4efa3b2c_o.gif",
        "link_bin": "https://github.com/lmbstudiocontact/mb5_33/raw/main/Frozen Cartoon_L5_1529528592_Russian.bin",
        "name_language": "Russian",
        "id_bin_language": "Frozen Cartoon_L5_1529528592_Russian"
      },
      {
        "author": "LMB Studio",
        "link_thumb": "https://live.staticflickr.com/65535/51698813120_ef964fda19_o.gif",
        "link_bin": "https://github.com/lmbstudiocontact/mb5_33/raw/main/Frozen Cartoon_L5_1529528592_Spanish.bin",
        "name_language": "Spanish",
        "id_bin_language": "Frozen Cartoon_L5_1529528592_Spanish"
      }
    ],
    "array_tags": [
      "lmbstudio"
    ],
    "list_album": [
      {
        "id_album": "995274074",
        "link_thumb": "https://live.staticflickr.com/65535/51697133377_c58343f90d_o.gif",
        "title": "Frozen Cartoon_L5"
      }
    ]
  },
  {
    "author": "LMB Studio",
    "link_thumb": "https://live.staticflickr.com/65535/51698605419_a78c5f98ee_o.gif",
    "link_bin": "https://github.com/lmbstudiocontact/mb5_33/raw/main/Frozen Cartoon_L5_1540577702.bin",
    "id_bin": "Frozen Cartoon_L5_1540577702",
    "list_language": [
      {
        "author": "LMB Studio",
        "link_thumb": "https://live.staticflickr.com/65535/51698205103_981536309b_o.gif",
        "link_bin": "https://github.com/lmbstudiocontact/mb5_33/raw/main/Frozen Cartoon_L5_1540577702_English.bin",
        "name_language": "English",
        "id_bin_language": "Frozen Cartoon_L5_1540577702_English"
      },
      {
        "author": "LMB Studio",
        "link_thumb": "https://live.staticflickr.com/65535/51697927526_96a7df6984_o.gif",
        "link_bin": "https://github.com/lmbstudiocontact/mb5_33/raw/main/Frozen Cartoon_L5_1540577702_Portuguese.bin",
        "name_language": "Portuguese",
        "id_bin_language": "Frozen Cartoon_L5_1540577702_Portuguese"
      },
      {
        "author": "LMB Studio",
        "link_thumb": "https://live.staticflickr.com/65535/51697136352_575d185e06_o.gif",
        "link_bin": "https://github.com/lmbstudiocontact/mb5_33/raw/main/Frozen Cartoon_L5_1540577702_Russian.bin",
        "name_language": "Russian",
        "id_bin_language": "Frozen Cartoon_L5_1540577702_Russian"
      },
      {
        "author": "LMB Studio",
        "link_thumb": "https://live.staticflickr.com/65535/51698206353_61f3590f0e_o.gif",
        "link_bin": "https://github.com/lmbstudiocontact/mb5_33/raw/main/Frozen Cartoon_L5_1540577702_Spanish.bin",
        "name_language": "Spanish",
        "id_bin_language": "Frozen Cartoon_L5_1540577702_Spanish"
      }
    ],
    "array_tags": [
      "lmbstudio"
    ],
    "list_album": [
      {
        "id_album": "995274074",
        "link_thumb": "https://live.staticflickr.com/65535/51698605419_a78c5f98ee_o.gif",
        "title": "Frozen Cartoon_L5"
      }
    ]
  },
  {
    "author": "LMB Studio",
    "link_thumb": "https://live.staticflickr.com/65535/51698206738_22a7092712_o.gif",
    "link_bin": "https://github.com/lmbstudiocontact/mb5_33/raw/main/Frozen Cartoon_L5_1651203574.bin",
    "id_bin": "Frozen Cartoon_L5_1651203574",
    "list_language": [
      {
        "author": "LMB Studio",
        "link_thumb": "https://live.staticflickr.com/65535/51698207238_82e1ca8af6_o.gif",
        "link_bin": "https://github.com/lmbstudiocontact/mb5_33/raw/main/Frozen Cartoon_L5_1651203574_English.bin",
        "name_language": "English",
        "id_bin_language": "Frozen Cartoon_L5_1651203574_English"
      },
      {
        "author": "LMB Studio",
        "link_thumb": "https://live.staticflickr.com/65535/51697138087_a5b69be7e6_o.gif",
        "link_bin": "https://github.com/lmbstudiocontact/mb5_33/raw/main/Frozen Cartoon_L5_1651203574_Portuguese.bin",
        "name_language": "Portuguese",
        "id_bin_language": "Frozen Cartoon_L5_1651203574_Portuguese"
      },
      {
        "author": "LMB Studio",
        "link_thumb": "https://live.staticflickr.com/65535/51698208083_0ba5d5cf03_o.gif",
        "link_bin": "https://github.com/lmbstudiocontact/mb5_33/raw/main/Frozen Cartoon_L5_1651203574_Russian.bin",
        "name_language": "Russian",
        "id_bin_language": "Frozen Cartoon_L5_1651203574_Russian"
      },
      {
        "author": "LMB Studio",
        "link_thumb": "https://live.staticflickr.com/65535/51698608939_2aaaf3d360_o.gif",
        "link_bin": "https://github.com/lmbstudiocontact/mb5_33/raw/main/Frozen Cartoon_L5_1651203574_Spanish.bin",
        "name_language": "Spanish",
        "id_bin_language": "Frozen Cartoon_L5_1651203574_Spanish"
      }
    ],
    "array_tags": [
      "lmbstudio"
    ],
    "list_album": [
      {
        "id_album": "995274074",
        "link_thumb": "https://live.staticflickr.com/65535/51698206738_22a7092712_o.gif",
        "title": "Frozen Cartoon_L5"
      }
    ]
  },
  {
    "author": "LMB Studio",
    "link_thumb": "https://live.staticflickr.com/65535/51697930936_2d1291ce42_o.gif",
    "link_bin": "https://github.com/lmbstudiocontact/mb5_33/raw/main/Frozen Cartoon_L5_224734855.bin",
    "id_bin": "Frozen Cartoon_L5_224734855",
    "list_language": [
      {
        "author": "LMB Studio",
        "link_thumb": "https://live.staticflickr.com/65535/51697931361_bdd63edcfb_o.gif",
        "link_bin": "https://github.com/lmbstudiocontact/mb5_33/raw/main/Frozen Cartoon_L5_224734855_English.bin",
        "name_language": "English",
        "id_bin_language": "Frozen Cartoon_L5_224734855_English"
      },
      {
        "author": "LMB Studio",
        "link_thumb": "https://live.staticflickr.com/65535/51698818440_95d3bd2f6e_o.gif",
        "link_bin": "https://github.com/lmbstudiocontact/mb5_33/raw/main/Frozen Cartoon_L5_224734855_Portuguese.bin",
        "name_language": "Portuguese",
        "id_bin_language": "Frozen Cartoon_L5_224734855_Portuguese"
      },
      {
        "author": "LMB Studio",
        "link_thumb": "https://live.staticflickr.com/65535/51697932116_23aff88fc0_o.gif",
        "link_bin": "https://github.com/lmbstudiocontact/mb5_33/raw/main/Frozen Cartoon_L5_224734855_Russian.bin",
        "name_language": "Russian",
        "id_bin_language": "Frozen Cartoon_L5_224734855_Russian"
      },
      {
        "author": "LMB Studio",
        "link_thumb": "https://live.staticflickr.com/65535/51697932411_2a5e7d4678_o.gif",
        "link_bin": "https://github.com/lmbstudiocontact/mb5_33/raw/main/Frozen Cartoon_L5_224734855_Spanish.bin",
        "name_language": "Spanish",
        "id_bin_language": "Frozen Cartoon_L5_224734855_Spanish"
      }
    ],
    "array_tags": [
      "lmbstudio"
    ],
    "list_album": [
      {
        "id_album": "995274074",
        "link_thumb": "https://live.staticflickr.com/65535/51697930936_2d1291ce42_o.gif",
        "title": "Frozen Cartoon_L5"
      }
    ]
  }
]