[
  {
    "author": "LMB Studio",
    "link_thumb": "https://live.staticflickr.com/65535/51703612911_553804ae10_o.gif",
    "link_bin": "https://github.com/lmbstudiocontact/mb5_25/raw/main/Sheep_L6_-944581431.bin",
    "id_bin": "Sheep_L6_-944581431",
    "list_language": [
      {
        "author": "LMB Studio",
        "link_thumb": "https://live.staticflickr.com/65535/51702818432_ce479a43af_o.gif",
        "link_bin": "https://github.com/lmbstudiocontact/mb5_25/raw/main/Sheep_L6_-944581431_English.bin",
        "name_language": "English",
        "id_bin_language": "Sheep_L6_-944581431_English"
      },
      {
        "author": "LMB Studio",
        "link_thumb": "https://live.staticflickr.com/65535/51703613181_562373e231_o.gif",
        "link_bin": "https://github.com/lmbstudiocontact/mb5_25/raw/main/Sheep_L6_-944581431_Portuguese.bin",
        "name_language": "Portuguese",
        "id_bin_language": "Sheep_L6_-944581431_Portuguese"
      },
      {
        "author": "LMB Studio",
        "link_thumb": "https://live.staticflickr.com/65535/51702818717_a208f12442_o.gif",
        "link_bin": "https://github.com/lmbstudiocontact/mb5_25/raw/main/Sheep_L6_-944581431_Russian.bin",
        "name_language": "Russian",
        "id_bin_language": "Sheep_L6_-944581431_Russian"
      },
      {
        "author": "LMB Studio",
        "link_thumb": "https://live.staticflickr.com/65535/51703613626_2df382eff8_o.gif",
        "link_bin": "https://github.com/lmbstudiocontact/mb5_25/raw/main/Sheep_L6_-944581431_Spanish.bin",
        "name_language": "Spanish",
        "id_bin_language": "Sheep_L6_-944581431_Spanish"
      }
    ],
    "array_tags": [
      "lmbstudio"
    ],
    "list_album": [
      {
        "id_album": "-576277778",
        "link_thumb": "https://live.staticflickr.com/65535/51703612911_553804ae10_o.gif",
        "title": "Sheep_L6"
      }
    ]
  },
  {
    "author": "LMB Studio",
    "link_thumb": "https://live.staticflickr.com/65535/51704502630_350e6da1c0_o.gif",
    "link_bin": "https://github.com/lmbstudiocontact/mb5_25/raw/main/Sheep_L6_-944583354.bin",
    "id_bin": "Sheep_L6_-944583354",
    "list_language": [
      {
        "author": "LMB Studio",
        "link_thumb": "https://live.staticflickr.com/65535/51704290639_cb7e8342ab_o.gif",
        "link_bin": "https://github.com/lmbstudiocontact/mb5_25/raw/main/Sheep_L6_-944583354_English.bin",
        "name_language": "English",
        "id_bin_language": "Sheep_L6_-944583354_English"
      },
      {
        "author": "LMB Studio",
        "link_thumb": "https://live.staticflickr.com/65535/51702819272_71834f6191_o.gif",
        "link_bin": "https://github.com/lmbstudiocontact/mb5_25/raw/main/Sheep_L6_-944583354_Portuguese.bin",
        "name_language": "Portuguese",
        "id_bin_language": "Sheep_L6_-944583354_Portuguese"
      },
      {
        "author": "LMB Studio",
        "link_thumb": "https://live.staticflickr.com/65535/51703614241_5d6c90146b_o.gif",
        "link_bin": "https://github.com/lmbstudiocontact/mb5_25/raw/main/Sheep_L6_-944583354_Russian.bin",
        "name_language": "Russian",
        "id_bin_language": "Sheep_L6_-944583354_Russian"
      },
      {
        "author": "LMB Studio",
        "link_thumb": "https://live.staticflickr.com/65535/51703896838_627b7b3d81_o.gif",
        "link_bin": "https://github.com/lmbstudiocontact/mb5_25/raw/main/Sheep_L6_-944583354_Spanish.bin",
        "name_language": "Spanish",
        "id_bin_language": "Sheep_L6_-944583354_Spanish"
      }
    ],
    "array_tags": [
      "lmbstudio"
    ],
    "list_album": [
      {
        "id_album": "-576277778",
        "link_thumb": "https://live.staticflickr.com/65535/51704502630_350e6da1c0_o.gif",
        "title": "Sheep_L6"
      }
    ]
  }
]